pdfdarkness/__init__.py
pdfdarkness/measure_darkness.py
pdfdarkness-0.1.0.dist-info/LICENSE
pdfdarkness-0.1.0.dist-info/METADATA
pdfdarkness-0.1.0.dist-info/WHEEL
pdfdarkness-0.1.0.dist-info/entry_points.txt
pdfdarkness-0.1.0.dist-info/top_level.txt
pdfdarkness-0.1.0.dist-info/RECORD
